batik/__init__.py
batik/__main__.py
batik/cli.py
batik/env.py
batik/layer.py
batik/manifest.py
batik/server.py
batik/commands/__init__.py
batik/commands/base.py
batik/commands/build.py
batik/commands/invoke.py
batik/commands/run.py
batik/commands/serve.py
batik/commands/validate.py
batik/frontends/__init__.py
batik/frontends/http_basic.py
batik-0.4.0.dist-info/METADATA
batik-0.4.0.dist-info/WHEEL
batik-0.4.0.dist-info/entry_points.txt
batik-0.4.0.dist-info/top_level.txt
batik-0.4.0.dist-info/RECORD
