Metadata-Version: 2.1
Name: batik
Version: 0.4.0
Summary: batik
Home-page: https://github.com/pfnsec/batik
Author: Peter Sherman
Author-email: pfnsec@gmail.com
License: MIT
Keywords: cli
Classifier: Intended Audience :: Developers
Classifier: Topic :: Utilities
Classifier: Natural Language :: English
Classifier: Operating System :: OS Independent
Classifier: Programming Language :: Python :: 3
Classifier: Programming Language :: Python :: 3.7
Classifier: Programming Language :: Python :: 3.8
Classifier: Programming Language :: Python :: 3.9
Classifier: Programming Language :: Python :: 3.10
Requires-Dist: aiohttp
Requires-Dist: pyyaml
Requires-Dist: watchdog
Requires-Dist: docopt
Requires-Dist: jinja2
Provides-Extra: test
Requires-Dist: coverage ; extra == 'test'
Requires-Dist: pytest ; extra == 'test'
Requires-Dist: pytest-cov ; extra == 'test'
